{"document":[{"columnCount":1,"type":"prompt","columns":[{"inDropZone":false,"field":{"id":1,"name":"","value":"","label":"","dataType":"","breakOrder":"","fieldOrder":"","tag":""},"alignment":"C"}],"reportName":"PO Accrual Report"},{"columnCount":1,"type":"table","columns":[{"inDropZone":false,"field":{"name":"BUSINESS_UNIT","value":"BUSINESS_UNIT","label":"BUSINESS_UNIT","fieldOrder":"1","breakOrder":"","dataType":"xsd:string","id":1},"alignment":"L"},{"inDropZone":false,"field":{"name":"PO_NUMBER","value":"PO_NUMBER","label":"PO_NUMBER","fieldOrder":"2","breakOrder":"","dataType":"xsd:string","id":2},"alignment":"L"},{"inDropZone":false,"field":{"name":"SUPPLIER_NAME","value":"SUPPLIER_NAME","label":"SUPPLIER_NAME","fieldOrder":"3","breakOrder":"","dataType":"xsd:string","id":3},"alignment":"L"},{"inDropZone":false,"field":{"name":"SUPPLIER_SITE_NAME","value":"SUPPLIER_SITE_NAME","label":"SUPPLIER_SITE_NAME","fieldOrder":"5","breakOrder":"","dataType":"xsd:string","id":4},"alignment":"L"},{"inDropZone":false,"field":{"name":"PO_LINE_NUMBER","value":"PO_LINE_NUMBER","label":"PO_LINE_NUMBER","fieldOrder":"7","breakOrder":"","dataType":"xsd:double","id":5},"alignment":"L"},{"inDropZone":false,"field":{"name":"PO_LINE_AMOUNT","value":"PO_LINE_AMOUNT","label":"PO_LINE_AMOUNT","fieldOrder":"13","breakOrder":"","dataType":"xsd:double","id":6},"alignment":"L"},{"inDropZone":false,"field":{"name":"PENDING_RECEIPTS_AMOUNT","value":"PENDING_RECEIPTS_AMOUNT","label":"PENDING_RECEIPTS_AMOUNT","fieldOrder":"25","breakOrder":"","dataType":"xsd:double","id":7},"alignment":"L"},{"inDropZone":false,"field":{"name":"PENDING_BILLING_AMOUNT","value":"PENDING_BILLING_AMOUNT","label":"PENDING_BILLING_AMOUNT","fieldOrder":"26","breakOrder":"","dataType":"xsd:double","id":8},"alignment":"L"},{"inDropZone":false,"field":{"name":"PO_DESC","value":"PO_DESC","label":"PO_DESC","fieldOrder":"32","breakOrder":"","dataType":"xsd:string","id":9},"alignment":"L"}],"showBorder":true,"reportName":"PO Accrual Report"}]}